fitbitApp/__init__.py
fitbitApp/fitbitApp.py
fitbitapp-1.1.0.dist-info/licenses/LICENSE
fitbitapp-1.1.0.dist-info/METADATA
fitbitapp-1.1.0.dist-info/WHEEL
fitbitapp-1.1.0.dist-info/top_level.txt
fitbitapp-1.1.0.dist-info/RECORD
