Metadata-Version: 2.4
Name: fitbitApp
Version: 1.1.0
Summary: fitbit WEB API wrapper
Home-page: https://github.com/gitpomtec/fitbitApp
Author: pom
Author-email: prgpom@gmail.com
License: BSD-3-Clause
Keywords: fitbit
Classifier: Development Status :: 5 - Production/Stable
Classifier: License :: OSI Approved :: BSD License
Classifier: Programming Language :: Python
Classifier: Programming Language :: Python :: 3.11
Classifier: Topic :: Database
Classifier: Topic :: Software Development :: Libraries :: Python Modules
License-File: LICENSE
Requires-Dist: Requests==2.32.5
Dynamic: author
Dynamic: author-email
Dynamic: classifier
Dynamic: description
Dynamic: home-page
Dynamic: keywords
Dynamic: license
Dynamic: license-file
Dynamic: requires-dist
Dynamic: summary
